mamba4rec/__init__.py
mamba4rec/dataset.py
mamba4rec/s3_tools.py
mamba4rec/s3_train.py
mamba4rec/train.py
mamba4rec-0.1.10.dist-info/licenses/LICENSE
mamba4rec-0.1.10.dist-info/METADATA
mamba4rec-0.1.10.dist-info/WHEEL
mamba4rec-0.1.10.dist-info/top_level.txt
mamba4rec-0.1.10.dist-info/RECORD
